pyderivationagent/__init__.py
pyderivationagent/agent/__init__.py
pyderivationagent/agent/derivation_agent.py
pyderivationagent/conf/__init__.py
pyderivationagent/conf/agent_conf.py
pyderivationagent/data_model/__init__.py
pyderivationagent/data_model/derivation.py
pyderivationagent/data_model/iris.py
pyderivationagent/data_model/utils.py
pyderivationagent/exception/__init__.py
pyderivationagent/exception/exception.py
pyderivationagent/kg_operations/__init__.py
pyderivationagent/kg_operations/derivation_client.py
pyderivationagent/kg_operations/gateway.py
pyderivationagent/kg_operations/sparql_client.py
pyderivationagent-1.6.0.dist-info/LICENSE
pyderivationagent-1.6.0.dist-info/METADATA
pyderivationagent-1.6.0.dist-info/WHEEL
pyderivationagent-1.6.0.dist-info/top_level.txt
pyderivationagent-1.6.0.dist-info/RECORD
