Metadata-Version: 2.1
Name: pyderivationagent
Version: 1.6.0
Summary: pyderivationagent is a python wrapper for derivation agents as part of The World Avatar project.
Home-page: https://github.com/cambridge-cares/TheWorldAvatar/tree/main/JPS_BASE_LIB/python_derivation_agent
Author: Jiaru Bai
Author-email: jb2197@cam.ac.uk
License: MIT
Requires-Python: >=3.5
License-File: LICENSE
Requires-Dist: py4jps (>=1.0.38)
Requires-Dist: flask (==2.1.0)
Requires-Dist: gunicorn (==20.0.4)
Requires-Dist: Flask-APScheduler
Requires-Dist: rdflib
Requires-Dist: python-dotenv
Requires-Dist: yagmail
Requires-Dist: Werkzeug (~=2.2.2)
Provides-Extra: dev
Requires-Dist: testcontainers (>=3.4.2) ; extra == 'dev'
Requires-Dist: pytest (>=6.2.3) ; extra == 'dev'
Requires-Dist: pytest-docker-compose (>=3.2.1) ; extra == 'dev'
Requires-Dist: pytest-rerunfailures (>=10.2) ; extra == 'dev'
